{
  "heroHighlights": [
    {
      "text": {
        "pt-BR": "Escuta individual para entender o momento, os limites e o desejo de cada pessoa.",
        "en": "One-on-one listening to understand each person's moment, boundaries, and desires.",
        "es": "Escucha individual para comprender el momento, los límites y el deseo de cada persona."
      }
    },
    {
      "text": {
        "pt-BR": "Ambiente estético e reservado, com luz suave, texturas orgânicas e clima de desaceleração.",
        "en": "Aesthetic and private surroundings with soft light, organic textures, and a slower rhythm.",
        "es": "Ambiente estético y reservado, con luz suave, texturas orgánicas y un ritmo desacelerado."
      }
    },
    {
      "text": {
        "pt-BR": "Condução sensorial sem pressa, respeitando o tempo, o consentimento e a presença corporal.",
        "en": "Unhurried sensory guidance that respects timing, consent, and embodied presence.",
        "es": "Conducción sensorial sin prisa, respetando el tiempo, el consentimiento y la presencia corporal."
      }
    },
    {
      "text": {
        "pt-BR": "Encerramento com integração e orientações para prolongar a experiência após o encontro.",
        "en": "Closing integration with guidance to extend the experience after the session.",
        "es": "Cierre con integración y orientaciones para prolongar la experiencia después del encuentro."
      }
    }
  ],
  "educationItems": [
    {
      "iconClass": "fas fa-comments",
      "title": {
        "pt-BR": "Escuta inicial",
        "en": "Initial conversation",
        "es": "Escucha inicial"
      },
      "institution": "01",
      "period": {
        "pt-BR": "Primeiro contato",
        "en": "First contact",
        "es": "Primer contacto"
      },
      "description": {
        "pt-BR": "Antes de qualquer vivência, Helen abre um espaço de conversa para entender contexto, expectativas e limites com transparência.",
        "en": "Before any experience, Helen creates a space for conversation to understand context, expectations, and boundaries with transparency.",
        "es": "Antes de cualquier vivencia, Helen abre un espacio de conversación para comprender contexto, expectativas y límites con transparencia."
      }
    },
    {
      "iconClass": "fas fa-feather-pointed",
      "title": {
        "pt-BR": "Preparação do ambiente",
        "en": "Atmosphere preparation",
        "es": "Preparación del ambiente"
      },
      "institution": "02",
      "period": {
        "pt-BR": "Chegada e acolhimento",
        "en": "Arrival and welcome",
        "es": "Llegada y acogida"
      },
      "description": {
        "pt-BR": "Texturas, música, aroma e temperatura criam um cenário sereno para que o corpo desacelere e a atenção se refine.",
        "en": "Textures, music, aroma, and temperature create a serene setting so the body can slow down and attention can sharpen.",
        "es": "Texturas, música, aroma y temperatura crean una escena serena para que el cuerpo desacelere y la atención se refine."
      }
    },
    {
      "iconClass": "fas fa-spa",
      "title": {
        "pt-BR": "Vivência guiada",
        "en": "Guided experience",
        "es": "Vivencia guiada"
      },
      "institution": "03",
      "period": {
        "pt-BR": "Durante o encontro",
        "en": "During the session",
        "es": "Durante el encuentro"
      },
      "description": {
        "pt-BR": "O ritmo do toque, da respiração e da presença é conduzido com suavidade, respeitando os sinais do corpo e aprofundando percepções.",
        "en": "The rhythm of touch, breath, and presence is guided with softness, respecting body cues and deepening perception.",
        "es": "El ritmo del toque, la respiración y la presencia se conduce con suavidad, respetando las señales del cuerpo y profundizando la percepción."
      }
    },
    {
      "iconClass": "fas fa-heart",
      "title": {
        "pt-BR": "Integração final",
        "en": "Closing integration",
        "es": "Integración final"
      },
      "institution": "04",
      "period": {
        "pt-BR": "Depois da experiência",
        "en": "After the experience",
        "es": "Después de la experiencia"
      },
      "description": {
        "pt-BR": "O encerramento prioriza aterramento e clareza, para que o que foi vivido possa reverberar com segurança no cotidiano.",
        "en": "The closing prioritizes grounding and clarity so the experience can resonate safely in everyday life.",
        "es": "El cierre prioriza arraigo y claridad para que lo vivido pueda resonar con seguridad en la vida cotidiana."
      }
    }
  ],
  "opportunityActions": [
    {
      "id": "opportunities-whatsapp",
      "variant": "primary",
      "contactKey": "whatsapp",
      "label": {
        "pt-BR": "Agendar pelo WhatsApp",
        "en": "Book via WhatsApp",
        "es": "Reservar por WhatsApp"
      },
      "openInNewTab": true
    },
    {
      "id": "opportunities-instagram",
      "variant": "secondary",
      "contactKey": "instagram",
      "label": {
        "pt-BR": "Ver Instagram",
        "en": "View Instagram",
        "es": "Ver Instagram"
      },
      "openInNewTab": true
    },
    {
      "id": "opportunities-email",
      "variant": "secondary",
      "contactKey": "email",
      "label": {
        "pt-BR": "Enviar e-mail",
        "en": "Send email",
        "es": "Enviar correo"
      },
      "openInNewTab": true
    }
  ]
}
